ysospy/__init__.py
ysospy/handy_scripts.py
ysospy/interpolation.py
ysospy/plotting_funcs.py
ysospy/variability.py
ysospy_noahbraunf-0.0.2.dist-info/LICENSE
ysospy_noahbraunf-0.0.2.dist-info/METADATA
ysospy_noahbraunf-0.0.2.dist-info/WHEEL
ysospy_noahbraunf-0.0.2.dist-info/top_level.txt
ysospy_noahbraunf-0.0.2.dist-info/RECORD
